CHANGELOG.txt
LICENSE.txt
MANIFEST.in
README.txt
setup.cfg
setup.py
obspyDMT/__init__.py
obspyDMT/obspyDMT.py
obspyDMT/process_unit.py
obspyDMT/process_unit_default.py
obspyDMT/process_unit_rename.py
obspyDMT/process_unit_rename_ami.py
obspyDMT/process_unit_sac.py
obspyDMT.egg-info/PKG-INFO
obspyDMT.egg-info/SOURCES.txt
obspyDMT.egg-info/dependency_links.txt
obspyDMT.egg-info/entry_points.txt
obspyDMT.egg-info/requires.txt
obspyDMT.egg-info/top_level.txt
obspyDMT/utils/__init__.py
obspyDMT/utils/data_handler.py
obspyDMT/utils/event_handler.py
obspyDMT/utils/input_handler.py
obspyDMT/utils/instrument_handler.py
obspyDMT/utils/kml_handler.py
obspyDMT/utils/local_handler.py
obspyDMT/utils/local_handler_BASEMAP.py
obspyDMT/utils/local_handler_CARTOPY.py
obspyDMT/utils/metadata_handler.py
obspyDMT/utils/plotxml_handler.py
obspyDMT/utils/resample_handler.py
obspyDMT/utils/spherical_nearest.py
obspyDMT/utils/utility_codes.py