Metadata-Version: 2.1
Name: obspyDMT
Version: 2.2.10
Summary: obspyDMT: A Python Toolbox for Retrieving, Processing and Management of Seismological Datasets
Home-page: https://github.com/kasra-hosseini/obspyDMT
Download-URL: https://github.com/kasra-hosseini/obspyDMT/archive/master.zip
Author: Kasra Hosseini
Author-email: k.hosseinizad@gmail.com
License: GNU Lesser General Public License, Version 3
Keywords: obspyDMT,obspy,seismology,geophysics
Platform: OS Independent
Classifier: Programming Language :: Python
Classifier: Development Status :: 4 - Beta
Classifier: Intended Audience :: Science/Research
Classifier: Operating System :: Unix
Classifier: Operating System :: Microsoft :: Windows
Classifier: Operating System :: MacOS
Classifier: Operating System :: OS Independent
Classifier: License :: OSI Approved :: GNU Library or Lesser General Public License (LGPL)
Classifier: Topic :: Software Development :: Libraries :: Python Modules
Classifier: Topic :: Scientific/Engineering
Classifier: Topic :: Scientific/Engineering :: Physics
License-File: LICENSE.txt
